cyberfusion/YAVB/__init__.py
cyberfusion/YAVB/enums.py
cyberfusion/YAVB/exceptions.py
cyberfusion/YAVB/systems.py
cyberfusion/YAVB/utilities.py
python3_cyberfusion_yavb-1.1.dist-info/METADATA
python3_cyberfusion_yavb-1.1.dist-info/WHEEL
python3_cyberfusion_yavb-1.1.dist-info/entry_points.txt
python3_cyberfusion_yavb-1.1.dist-info/top_level.txt
python3_cyberfusion_yavb-1.1.dist-info/RECORD
