Metadata-Version: 2.4
Name: python3-cyberfusion-yavb
Version: 1.1
Summary: Version bumper for software projects.
Author-email: Cyberfusion <support@cyberfusion.io>
Project-URL: Source, https://github.com/CyberfusionIO/python3-cyberfusion-yavb
Requires-Dist: semver==3.0.2
Requires-Dist: typer==0.15.2
Requires-Dist: tomlkit==0.13.2
